[
  {
    "title": "정보시스템 기반 기술",
    "comments": [
      {
        "problem_number": 1,
        "comment": "정답 선택지가 문제에서 요구한 개념/규칙/결과에 가장 정확하게 부합합니다."
      },
      {
        "problem_number": 2,
        "comment": "정답 선택지가 문제에서 요구한 개념/규칙/결과에 가장 정확하게 부합합니다."
      },
      {
        "problem_number": 3,
        "comment": "정답 선택지가 문제에서 요구한 개념/규칙/결과에 가장 정확하게 부합합니다."
      },
      {
        "problem_number": 4,
        "comment": "Preemption입니다. 다른 선택지는 용어의 의미나 적용 범위가 달라 문제의 조건에 맞지 않습니다."
      },
      {
        "problem_number": 5,
        "comment": "전송 계층입니다. 다른 선택지는 용어의 의미나 적용 범위가 달라 문제의 조건에 맞지 않습니다."
      },
      {
        "problem_number": 6,
        "comment": "문항의 조건에 따라 계산 또는 규칙을 적용하면 결과값은 790입니다. 따라서 790를 고르는 것이 맞습니다."
      },
      {
        "problem_number": 7,
        "comment": "정답 선택지가 문제에서 요구한 개념/규칙/결과에 가장 정확하게 부합합니다."
      },
      {
        "problem_number": 8,
        "comment": "프로토콜입니다. 다른 선택지는 용어의 의미나 적용 범위가 달라 문제의 조건에 맞지 않습니다."
      },
      {
        "problem_number": 9,
        "comment": "정답 선택지가 문제에서 요구한 개념/규칙/결과에 가장 정확하게 부합합니다."
      },
      {
        "problem_number": 10,
        "comment": "문항의 조건에 따라 계산 또는 규칙을 적용하면 결과값은 15입니다. 따라서 15를 고르는 것이 맞습니다."
      },
      {
        "problem_number": 11,
        "comment": "Observer입니다. 다른 선택지는 용어의 의미나 적용 범위가 달라 문제의 조건에 맞지 않습니다."
      },
      {
        "problem_number": 12,
        "comment": "정답 선택지가 문제에서 요구한 개념/규칙/결과에 가장 정확하게 부합합니다."
      },
      {
        "problem_number": 13,
        "comment": "정답 선택지가 문제에서 요구한 개념/규칙/결과에 가장 정확하게 부합합니다."
      },
      {
        "problem_number": 14,
        "comment": "연산식 반복입니다. 다른 선택지는 용어의 의미나 적용 범위가 달라 문제의 조건에 맞지 않습니다."
      },
      {
        "problem_number": 15,
        "comment": "Synonym입니다. 다른 선택지는 용어의 의미나 적용 범위가 달라 문제의 조건에 맞지 않습니다."
      },
      {
        "problem_number": 16,
        "comment": "해밍(Hamming) 코드입니다. 다른 선택지는 용어의 의미나 적용 범위가 달라 문제의 조건에 맞지 않습니다."
      },
      {
        "problem_number": 17,
        "comment": "네트워크 계층입니다. 다른 선택지는 용어의 의미나 적용 범위가 달라 문제의 조건에 맞지 않습니다."
      },
      {
        "problem_number": 18,
        "comment": "추상 클래스입니다. 다른 선택지는 용어의 의미나 적용 범위가 달라 문제의 조건에 맞지 않습니다."
      },
      {
        "problem_number": 19,
        "comment": "UML입니다. 다른 선택지는 용어의 의미나 적용 범위가 달라 문제의 조건에 맞지 않습니다."
      },
      {
        "problem_number": 20,
        "comment": "정답 선택지가 문제에서 요구한 개념/규칙/결과에 가장 정확하게 부합합니다."
      }
    ]
  },
  {
    "title": "프로그래밍 언어 활용",
    "comments": [
      {
        "problem_number": 21,
        "comment": "내용 결합도입니다. 다른 선택지는 용어의 의미나 적용 범위가 달라 문제의 조건에 맞지 않습니다."
      },
      {
        "problem_number": 22,
        "comment": "Vulnerability입니다. 다른 선택지는 용어의 의미나 적용 범위가 달라 문제의 조건에 맞지 않습니다."
      },
      {
        "problem_number": 23,
        "comment": "return입니다. 다른 선택지는 용어의 의미나 적용 범위가 달라 문제의 조건에 맞지 않습니다."
      },
      {
        "problem_number": 24,
        "comment": "getchar( )입니다. 다른 선택지는 용어의 의미나 적용 범위가 달라 문제의 조건에 맞지 않습니다."
      },
      {
        "problem_number": 25,
        "comment": "정답 선택지가 문제에서 요구한 개념/규칙/결과에 가장 정확하게 부합합니다."
      },
      {
        "problem_number": 26,
        "comment": "%x - 정수형 8진수입니다. 다른 선택지는 용어의 의미나 적용 범위가 달라 문제의 조건에 맞지 않습니다."
      },
      {
        "problem_number": 27,
        "comment": "Range입니다. 다른 선택지는 용어의 의미나 적용 범위가 달라 문제의 조건에 맞지 않습니다."
      },
      {
        "problem_number": 28,
        "comment": "3edc입니다. 다른 선택지는 용어의 의미나 적용 범위가 달라 문제의 조건에 맞지 않습니다."
      },
      {
        "problem_number": 29,
        "comment": "더미코드 재사용입니다. 다른 선택지는 용어의 의미나 적용 범위가 달라 문제의 조건에 맞지 않습니다."
      },
      {
        "problem_number": 30,
        "comment": "정답 선택지가 문제에서 요구한 개념/규칙/결과에 가장 정확하게 부합합니다."
      },
      {
        "problem_number": 31,
        "comment": "Django 3회입니다. 다른 선택지는 용어의 의미나 적용 범위가 달라 문제의 조건에 맞지 않습니다."
      },
      {
        "problem_number": 32,
        "comment": "정답 선택지가 문제에서 요구한 개념/규칙/결과에 가장 정확하게 부합합니다."
      },
      {
        "problem_number": 33,
        "comment": "정답 선택지가 문제에서 요구한 개념/규칙/결과에 가장 정확하게 부합합니다."
      },
      {
        "problem_number": 34,
        "comment": "required입니다. 다른 선택지는 용어의 의미나 적용 범위가 달라 문제의 조건에 맞지 않습니다."
      },
      {
        "problem_number": 35,
        "comment": "문항의 조건에 따라 계산 또는 규칙을 적용하면 결과값은 2입니다. 따라서 2를 고르는 것이 맞습니다."
      },
      {
        "problem_number": 36,
        "comment": "정답 선택지가 문제에서 요구한 개념/규칙/결과에 가장 정확하게 부합합니다."
      },
      {
        "problem_number": 37,
        "comment": "결합도입니다. 다른 선택지는 용어의 의미나 적용 범위가 달라 문제의 조건에 맞지 않습니다."
      },
      {
        "problem_number": 38,
        "comment": "&&입니다. 다른 선택지는 용어의 의미나 적용 범위가 달라 문제의 조건에 맞지 않습니다."
      },
      {
        "problem_number": 39,
        "comment": "alert입니다. 다른 선택지는 용어의 의미나 적용 범위가 달라 문제의 조건에 맞지 않습니다."
      },
      {
        "problem_number": 40,
        "comment": "다른 모듈에서의 접근이 불가능해야 한다. 제3과목 : 데이터베이스 활용"
      }
    ]
  },
  {
    "title": "데이터베이스의 활용",
    "comments": [
      {
        "problem_number": 41,
        "comment": "정답 선택지가 문제에서 요구한 개념/규칙/결과에 가장 정확하게 부합합니다."
      },
      {
        "problem_number": 42,
        "comment": "3NF → BCNF입니다. 다른 선택지는 용어의 의미나 적용 범위가 달라 문제의 조건에 맞지 않습니다."
      },
      {
        "problem_number": 43,
        "comment": "정답 선택지가 문제에서 요구한 개념/규칙/결과에 가장 정확하게 부합합니다."
      },
      {
        "problem_number": 44,
        "comment": "정답 선택지가 문제에서 요구한 개념/규칙/결과에 가장 정확하게 부합합니다."
      },
      {
        "problem_number": 45,
        "comment": "부분 함수 종속성 제거입니다. 다른 선택지는 용어의 의미나 적용 범위가 달라 문제의 조건에 맞지 않습니다."
      },
      {
        "problem_number": 46,
        "comment": "정답 선택지가 문제에서 요구한 개념/규칙/결과에 가장 정확하게 부합합니다."
      },
      {
        "problem_number": 47,
        "comment": "정답 선택지가 문제에서 요구한 개념/규칙/결과에 가장 정확하게 부합합니다."
      },
      {
        "problem_number": 48,
        "comment": "정답 선택지가 문제에서 요구한 개념/규칙/결과에 가장 정확하게 부합합니다."
      },
      {
        "problem_number": 49,
        "comment": "도메인입니다. 다른 선택지는 용어의 의미나 적용 범위가 달라 문제의 조건에 맞지 않습니다."
      },
      {
        "problem_number": 50,
        "comment": "운영 기능입니다. 다른 선택지는 용어의 의미나 적용 범위가 달라 문제의 조건에 맞지 않습니다."
      },
      {
        "problem_number": 51,
        "comment": "개체 무결성 제약 조건입니다. 다른 선택지는 용어의 의미나 적용 범위가 달라 문제의 조건에 맞지 않습니다."
      },
      {
        "problem_number": 52,
        "comment": "SELECT입니다. 다른 선택지는 용어의 의미나 적용 범위가 달라 문제의 조건에 맞지 않습니다."
      },
      {
        "problem_number": 53,
        "comment": "정답 선택지가 문제에서 요구한 개념/규칙/결과에 가장 정확하게 부합합니다."
      },
      {
        "problem_number": 54,
        "comment": "Distribution입니다. 다른 선택지는 용어의 의미나 적용 범위가 달라 문제의 조건에 맞지 않습니다."
      },
      {
        "problem_number": 55,
        "comment": "문항의 조건에 따라 계산 또는 규칙을 적용하면 결과값은 20입니다. 따라서 20를 고르는 것이 맞습니다."
      },
      {
        "problem_number": 56,
        "comment": "정답 선택지가 문제에서 요구한 개념/규칙/결과에 가장 정확하게 부합합니다."
      },
      {
        "problem_number": 57,
        "comment": "Stack입니다. 다른 선택지는 용어의 의미나 적용 범위가 달라 문제의 조건에 맞지 않습니다."
      },
      {
        "problem_number": 58,
        "comment": "직접 파일입니다. 다른 선택지는 용어의 의미나 적용 범위가 달라 문제의 조건에 맞지 않습니다."
      },
      {
        "problem_number": 59,
        "comment": "정답 선택지가 문제에서 요구한 개념/규칙/결과에 가장 정확하게 부합합니다."
      },
      {
        "problem_number": 60,
        "comment": "정답 선택지가 문제에서 요구한 개념/규칙/결과에 가장 정확하게 부합합니다."
      }
    ]
  }
]
